dragonBallSearch/__init__.py
dragonBallSearch/module.py
dragonBallSearch-0.0.1.dist-info/METADATA
dragonBallSearch-0.0.1.dist-info/WHEEL
dragonBallSearch-0.0.1.dist-info/top_level.txt
dragonBallSearch-0.0.1.dist-info/RECORD
