Metadata-Version: 2.1
Name: dragonBallSearch
Version: 0.0.1
Summary: dragonBallSearch
Home-page: https://github.com/hodragon5237
Author: hodragon
Author-email: giddens5237@gmail.com
License: BEERWARE
Platform: UNKNOWN
Classifier: Programming Language :: Python :: 3
Classifier: Operating System :: OS Independent
